xspfclean-0.3.data/scripts/xspfclean
xspfcleaner/__init__.py
xspfcleaner/cleaner.py
xspfclean-0.3.dist-info/LICENSE
xspfclean-0.3.dist-info/METADATA
xspfclean-0.3.dist-info/WHEEL
xspfclean-0.3.dist-info/top_level.txt
xspfclean-0.3.dist-info/RECORD
