Metadata-Version: 2.1
Name: xspfclean
Version: 0.3
Summary: Xspf playlist files cleaner
Home-page: https://github.com/eibrahim995/xspfcleaner
Author: Ibrahim E.Gad
Author-email: eibrahim995@yandex.com
License: UNKNOWN
Platform: UNKNOWN
Classifier: Programming Language :: Python :: 3
Classifier: License :: OSI Approved :: Common Public License
Classifier: Operating System :: OS Independent
Requires-Dist: python-magic
